natlibpy/__init__.py
natlibpy/factory.py
natlibpy-1.0.0.dist-info/LICENSE
natlibpy-1.0.0.dist-info/METADATA
natlibpy-1.0.0.dist-info/WHEEL
natlibpy-1.0.0.dist-info/top_level.txt
natlibpy-1.0.0.dist-info/RECORD
