Metadata-Version: 2.1
Name: natlibpy
Version: 1.0.0
Summary: Code I find myself reusing often
Home-page: https://github.com/narthur/natlibpy
Author: Nathan Arthur
Author-email: nathan@nathanarthur.com
License: MIT
Platform: UNKNOWN
Classifier: License :: OSI Approved :: MIT License
Classifier: Programming Language :: Python :: 3
Classifier: Programming Language :: Python :: 3.7
